prompt/__init__.py
prompt/cli.py
promptcli-2.1.0.dist-info/LICENSE
promptcli-2.1.0.dist-info/METADATA
promptcli-2.1.0.dist-info/WHEEL
promptcli-2.1.0.dist-info/entry_points.txt
promptcli-2.1.0.dist-info/top_level.txt
promptcli-2.1.0.dist-info/RECORD
