Metadata-Version: 2.1
Name: promptcli
Version: 2.1.0
Summary: A command line application to help wrap the OpenAI ChatGPT api.
Home-page: https://github.com/raiyanyahya/prompt
Author: Raiyan Yahya
Author-email: raiyanyahyadeveloper@gmail.com
License: MIT
Keywords: cli,developer tools,productivity,openai,chatgpt
Platform: UNKNOWN
Requires-Python: >3.5
Requires-Dist: click ==8.1.3
Requires-Dist: openai ==0.27.8
Requires-Dist: rich ==13.4.1
